{
    "parent":"main:general/kill/4",
    "display":{
        "icon":{
            "id":"diamond_sword"
        },
        "title":[
            {
                "translate":"ms.adv.kill.5",
                "fallback":"四百年来成一梦"
            }
        ],
        "description":[
            {
                "translate":"ms.goal.kill",
                "fallback":"· 累计击杀 %s 个灵魂",
                "with":[
                    "400"
                ],
                "color":"white"
            },
            "\n\n",
            {
                "translate":"ms.adv.kill.5.desc",
                "fallback":"长夜无尽",
                "color":"gray",
                "italic":true
            },
            "\n\n",
            {
                "translate":"ms.adv.pts",
                "fallback":"💠 进度点 +%s",
                "with":[
                    "20"
                ],
                "color":"aqua"
            }
        ],
        "frame":"challenge",
        "hidden":true
    },
    "criteria":{
        "kill_single":{
            "trigger":"location",
            "conditions":{
                "player":[
                    {
                        "scores":{
                            "stat.kill":{
                                "min":400
                            }
                        },
                        "condition":"entity_scores",
                        "entity":"this"
                    }
                ]
            }
        }
    },
    "rewards":{
        "function":"main:lib/advancement/prize/20"
    }
}